mobio_license_sdk-1.0.11-py3.9-nspkg.pth
mobio/sdks/license/__init__.py
mobio/sdks/license/call_api.py
mobio/sdks/license/config.py
mobio/sdks/license/crypt_utils.py
mobio/sdks/license/date_utils.py
mobio/sdks/license/license_detail_mess_used.py
mobio/sdks/license/license_history_mess_used.py
mobio/sdks/license/license_mess_used.py
mobio/sdks/license/license_sdk.py
mobio/sdks/license/mongo_connection.py
mobio/sdks/license/utils.py
mobio_license_sdk-1.0.11.dist-info/METADATA
mobio_license_sdk-1.0.11.dist-info/WHEEL
mobio_license_sdk-1.0.11.dist-info/namespace_packages.txt
mobio_license_sdk-1.0.11.dist-info/top_level.txt
mobio_license_sdk-1.0.11.dist-info/RECORD
